INSTALL.rst
LICENSE
MANIFEST.in
README.rst
VERSION
setup.py
tasks.py
src/lazyutils/__init__.py
src/lazyutils/__main__.py
src/lazyutils/__meta__.py
src/lazyutils/core.py
src/lazyutils.egg-info/PKG-INFO
src/lazyutils.egg-info/SOURCES.txt
src/lazyutils.egg-info/dependency_links.txt
src/lazyutils.egg-info/not-zip-safe
src/lazyutils.egg-info/requires.txt
src/lazyutils.egg-info/top_level.txt
src/lazyutils/tests/__init__.py
src/lazyutils/tests/__main__.py
src/lazyutils/tests/test_documentation.py
src/lazyutils/tests/test_lazyutils.py