Metadata-Version: 1.1
Name: lazyutils
Version: 0.3.3
Summary: Lazy accessor and other tools for deferred evaluation.
Home-page: http://github.com/fabiommendes/lazyutils/
Author: Fábio Macêdo Mendes
Author-email: fabiomacedomendes@gmail.com
License: UNKNOWN
Platform: any
Classifier: Development Status :: 5 - Production/Stable
Classifier: Intended Audience :: Developers
Classifier: License :: OSI Approved :: GNU General Public License (GPL)
Classifier: Programming Language :: Python
Classifier: Topic :: Software Development :: Libraries
